Source/AssetPack.py
Source/AssetPacker.py
Source/__init__.py
Resource_Packer-1.0.dist-info/LICENSE
Resource_Packer-1.0.dist-info/METADATA
Resource_Packer-1.0.dist-info/WHEEL
Resource_Packer-1.0.dist-info/entry_points.txt
Resource_Packer-1.0.dist-info/top_level.txt
Resource_Packer-1.0.dist-info/RECORD
