Metadata-Version: 2.1
Name: Resource-Packer
Version: 1.0
Summary: A commandline tool to convert assets into source code
Home-page: https://github.com/R00tDroid/ResourcePacker
Author: R00tDroid
License: MIT
License-File: LICENSE
